osc_npyscreen/__init__.py
osc_npyscreen/apNPSApplication.py
osc_npyscreen/apNPSApplicationAdvanced.py
osc_npyscreen/apNPSApplicationEvents.py
osc_npyscreen/apNPSApplicationManaged.py
osc_npyscreen/apOptions.py
osc_npyscreen/eveventhandler.py
osc_npyscreen/fmActionForm.py
osc_npyscreen/fmActionFormV2.py
osc_npyscreen/fmFileSelector.py
osc_npyscreen/fmForm.py
osc_npyscreen/fmFormMultiPage.py
osc_npyscreen/fmFormMutt.py
osc_npyscreen/fmFormMuttActive.py
osc_npyscreen/fmFormWithMenus.py
osc_npyscreen/fmPopup.py
osc_npyscreen/fm_form_edit_loop.py
osc_npyscreen/globals.py
osc_npyscreen/muMenu.py
osc_npyscreen/muNewMenu.py
osc_npyscreen/npysGlobalOptions.py
osc_npyscreen/npysNPSFilteredData.py
osc_npyscreen/npysThemeManagers.py
osc_npyscreen/npysThemes.py
osc_npyscreen/npysTree.py
osc_npyscreen/npyspmfuncs.py
osc_npyscreen/npyssafewrapper.py
osc_npyscreen/proto_fm_screen_area.py
osc_npyscreen/stdfmemail.py
osc_npyscreen/utilNotify.py
osc_npyscreen/util_viewhelp.py
osc_npyscreen/wgFormControlCheckbox.py
osc_npyscreen/wgNMenuDisplay.py
osc_npyscreen/wgannotatetextbox.py
osc_npyscreen/wgautocomplete.py
osc_npyscreen/wgboxwidget.py
osc_npyscreen/wgbutton.py
osc_npyscreen/wgcheckbox.py
osc_npyscreen/wgcombobox.py
osc_npyscreen/wgdatecombo.py
osc_npyscreen/wgeditmultiline.py
osc_npyscreen/wgfilenamecombo.py
osc_npyscreen/wggrid.py
osc_npyscreen/wggridcoltitles.py
osc_npyscreen/wgmonthbox.py
osc_npyscreen/wgmultiline.py
osc_npyscreen/wgmultilineeditable.py
osc_npyscreen/wgmultilinetree.py
osc_npyscreen/wgmultilinetreeselectable.py
osc_npyscreen/wgmultiselect.py
osc_npyscreen/wgmultiselecttree.py
osc_npyscreen/wgpassword.py
osc_npyscreen/wgselectone.py
osc_npyscreen/wgslider.py
osc_npyscreen/wgtextbox.py
osc_npyscreen/wgtextbox_controlchrs.py
osc_npyscreen/wgtextboxunicode.py
osc_npyscreen/wgtexttokens.py
osc_npyscreen/wgtitlefield.py
osc_npyscreen/wgwidget.py
osc_npyscreen/wgwidget_proto.py
osc_npyscreen/compatibility_code/__init__.py
osc_npyscreen-4.9.2.dist-info/LICENCE
osc_npyscreen-4.9.2.dist-info/METADATA
osc_npyscreen-4.9.2.dist-info/WHEEL
osc_npyscreen-4.9.2.dist-info/top_level.txt
osc_npyscreen-4.9.2.dist-info/RECORD
