Metadata-Version: 2.1
Name: osc_npyscreen
Version: 4.9.2
Summary: Writing user interfaces without all that ugly mucking about in hyperspace
Home-page: http://www.npcole.com/osc_npyscreen/
Author: Nicholas Cole
Author-email: n@npcole.com
License: New BSD License
Classifier: Development Status :: 5 - Production/Stable
Classifier: Programming Language :: Python :: 3
Classifier: Programming Language :: Python :: 2.6
Classifier: Programming Language :: Python :: 2.7
Classifier: Environment :: Console
Classifier: Operating System :: POSIX
Classifier: Environment :: Console :: Curses
Classifier: Intended Audience :: Developers
Classifier: License :: OSI Approved :: BSD License
Classifier: Topic :: Terminals
License-File: LICENCE
